{
    "results":[
       {
          "gender":"male",
          "name":{
             "title":"Mr",
             "first":"اميرعلي",
             "last":"جعفری"
          },
          "location":{
             "street":{
                "number":9529,
                "name":"پارک 17 شهریور"
             },
             "city":"رشت",
             "state":"قم",
             "country":"Iran",
             "postcode":20322,
             "coordinates":{
                "latitude":"13.6196",
                "longitude":"-97.9669"
             },
             "timezone":{
                "offset":"-4:00",
                "description":"Atlantic Time (Canada), Caracas, La Paz"
             }
          },
          "email":"myraaly.jaafry@example.com",
          "login":{
             "uuid":"214fe681-a0da-4cab-890d-0594b63b0174",
             "username":"beautifulswan101",
             "password":"michelle",
             "salt":"Pc1OXQTq",
             "md5":"b98925aca18494bc852aea4d52ae6a5c",
             "sha1":"7a1dfc6e151b40a5b47cdec5d15da058625fd465",
             "sha256":"0419b6df5453923363f1112b34817aa519893e71a71290837074bf82d135f885"
          },
          "dob":{
             "date":"1963-01-05T09:39:15.864Z",
             "age":59
          },
          "registered":{
             "date":"2014-04-29T14:38:20.196Z",
             "age":8
          },
          "phone":"074-27004241",
          "cell":"0980-978-5755",
          "id":{
             "name":"",
             "value":null
          },
          "picture":{
             "large":"https://randomuser.me/api/portraits/men/25.jpg",
             "medium":"https://randomuser.me/api/portraits/med/men/25.jpg",
             "thumbnail":"https://randomuser.me/api/portraits/thumb/men/25.jpg"
          },
          "nat":"IR"
       },
       {
          "gender":"female",
          "name":{
             "title":"Mrs",
             "first":"Crystal",
             "last":"Russell"
          },
          "location":{
             "street":{
                "number":2263,
                "name":"Pecan Acres Ln"
             },
             "city":"Bunbury",
             "state":"Tasmania",
             "country":"Australia",
             "postcode":9581,
             "coordinates":{
                "latitude":"-2.4942",
                "longitude":"-127.5903"
             },
             "timezone":{
                "offset":"-12:00",
                "description":"Eniwetok, Kwajalein"
             }
          },
          "email":"crystal.russell@example.com",
          "login":{
             "uuid":"d0fcd9b9-8093-4c60-b93a-3a188629cc07",
             "username":"beautifulladybug966",
             "password":"scania",
             "salt":"OdIHxlKU",
             "md5":"99845b57a319d3b109524bf3dac996fc",
             "sha1":"33f52bc0afd6db81e29cddae56fdf9d7141c6705",
             "sha256":"d7333508b63a7868ed2eb384d10ce932744c81d1ba23a3693904273e2b05ef38"
          },
          "dob":{
             "date":"1994-09-27T00:46:43.016Z",
             "age":28
          },
          "registered":{
             "date":"2016-12-15T13:40:46.058Z",
             "age":5
          },
          "phone":"07-2831-6460",
          "cell":"0429-015-385",
          "id":{
             "name":"TFN",
             "value":"284408257"
          },
          "picture":{
             "large":"https://randomuser.me/api/portraits/women/25.jpg",
             "medium":"https://randomuser.me/api/portraits/med/women/25.jpg",
             "thumbnail":"https://randomuser.me/api/portraits/thumb/women/25.jpg"
          },
          "nat":"AU"
       },
       {
          "gender":"male",
          "name":{
             "title":"Mr",
             "first":"Okan",
             "last":"Kahveci"
          },
          "location":{
             "street":{
                "number":9973,
                "name":"Talak Göktepe Cd"
             },
             "city":"Manisa",
             "state":"Kırklareli",
             "country":"Turkey",
             "postcode":85004,
             "coordinates":{
                "latitude":"83.3729",
                "longitude":"137.6983"
             },
             "timezone":{
                "offset":"+3:00",
                "description":"Baghdad, Riyadh, Moscow, St. Petersburg"
             }
          },
          "email":"okan.kahveci@example.com",
          "login":{
             "uuid":"b4b3d52a-7a14-4e02-96d9-3d770e39cfe7",
             "username":"lazyfrog974",
             "password":"solution",
             "salt":"xxntjK3i",
             "md5":"63445365936afdfa1d4a0e692a2a38a5",
             "sha1":"3b6fa4f9cf9cc5df76f69158d8d0aed0a9985474",
             "sha256":"dab324a1e968fd074ed5a0839a7e3114d24cf4219aa573dbc5f2824973b869d2"
          },
          "dob":{
             "date":"1958-04-20T07:07:50.234Z",
             "age":64
          },
          "registered":{
             "date":"2004-02-19T22:21:25.075Z",
             "age":18
          },
          "phone":"(146)-806-3403",
          "cell":"(669)-285-6176",
          "id":{
             "name":"",
             "value":null
          },
          "picture":{
             "large":"https://randomuser.me/api/portraits/men/99.jpg",
             "medium":"https://randomuser.me/api/portraits/med/men/99.jpg",
             "thumbnail":"https://randomuser.me/api/portraits/thumb/men/99.jpg"
          },
          "nat":"TR"
       },
       {
          "gender":"female",
          "name":{
             "title":"Mrs",
             "first":"Ronja",
             "last":"Lehto"
          },
          "location":{
             "street":{
                "number":1340,
                "name":"Visiokatu"
             },
             "city":"Hanko",
             "state":"Kymenlaakso",
             "country":"Finland",
             "postcode":94667,
             "coordinates":{
                "latitude":"55.8443",
                "longitude":"-18.3734"
             },
             "timezone":{
                "offset":"-9:00",
                "description":"Alaska"
             }
          },
          "email":"ronja.lehto@example.com",
          "login":{
             "uuid":"8f487d66-3529-4e2d-b5f3-1f26ad095616",
             "username":"lazysnake603",
             "password":"shamrock",
             "salt":"ChNU3Zl0",
             "md5":"50f43b5c8d28529ee0793644676ac904",
             "sha1":"1c1db1a4273009cfa8e57f5d0a21b669de8957aa",
             "sha256":"f52e68ee936c8250b6cf1b5eab266d2bfeb6f9afc9d443321e1932d1b5ab9836"
          },
          "dob":{
             "date":"1993-02-27T15:07:54.598Z",
             "age":29
          },
          "registered":{
             "date":"2014-02-21T08:37:00.341Z",
             "age":8
          },
          "phone":"04-839-161",
          "cell":"048-315-07-31",
          "id":{
             "name":"HETU",
             "value":"NaNNA366undefined"
          },
          "picture":{
             "large":"https://randomuser.me/api/portraits/women/91.jpg",
             "medium":"https://randomuser.me/api/portraits/med/women/91.jpg",
             "thumbnail":"https://randomuser.me/api/portraits/thumb/women/91.jpg"
          },
          "nat":"FI"
       },
       {
          "gender":"female",
          "name":{
             "title":"Miss",
             "first":"Eleanor",
             "last":"Silva"
          },
          "location":{
             "street":{
                "number":7155,
                "name":"York Road"
             },
             "city":"Westminster",
             "state":"Lancashire",
             "country":"United Kingdom",
             "postcode":"S6 0WZ",
             "coordinates":{
                "latitude":"21.4941",
                "longitude":"47.7702"
             },
             "timezone":{
                "offset":"-6:00",
                "description":"Central Time (US & Canada), Mexico City"
             }
          },
          "email":"eleanor.silva@example.com",
          "login":{
             "uuid":"f4c9a2c9-5bc7-4712-b13f-71aced2fc8d8",
             "username":"yellowbear545",
             "password":"amelia",
             "salt":"nqGJKFhb",
             "md5":"ff4eae8891eeaf3b36f299a467262928",
             "sha1":"644aadd3ac7471345a3c7e4516fe8aa0e1852a92",
             "sha256":"52b86b7de75db1942be67435fbd0f3138b4443a73af6ae4fc716085b1a3f17d1"
          },
          "dob":{
             "date":"1952-12-19T20:57:34.307Z",
             "age":69
          },
          "registered":{
             "date":"2012-04-16T09:20:27.460Z",
             "age":10
          },
          "phone":"016974 54119",
          "cell":"07012 775397",
          "id":{
             "name":"NINO",
             "value":"SS 54 91 70 I"
          },
          "picture":{
             "large":"https://randomuser.me/api/portraits/women/46.jpg",
             "medium":"https://randomuser.me/api/portraits/med/women/46.jpg",
             "thumbnail":"https://randomuser.me/api/portraits/thumb/women/46.jpg"
          },
          "nat":"GB"
       },
       {
          "gender":"female",
          "name":{
             "title":"Mrs",
             "first":"Malou",
             "last":"Poulsen"
          },
          "location":{
             "street":{
                "number":9446,
                "name":"Ellemosevej"
             },
             "city":"Haslev",
             "state":"Sjælland",
             "country":"Denmark",
             "postcode":74088,
             "coordinates":{
                "latitude":"63.8443",
                "longitude":"32.7712"
             },
             "timezone":{
                "offset":"-12:00",
                "description":"Eniwetok, Kwajalein"
             }
          },
          "email":"malou.poulsen@example.com",
          "login":{
             "uuid":"f5e5e193-d529-41b5-a699-684d43bfe973",
             "username":"crazyswan634",
             "password":"1957",
             "salt":"4wmYhXqm",
             "md5":"d9385965af909a88ddd368c85fc01ae9",
             "sha1":"d521d3d5c8b057041a71d4144e6d8e7e90d4caeb",
             "sha256":"05b969aaa0c1080f8072b28fb8f3681e5373ab75d4831cf60804ceaf750bb41c"
          },
          "dob":{
             "date":"1987-03-14T11:11:56.921Z",
             "age":35
          },
          "registered":{
             "date":"2003-07-07T07:31:49.376Z",
             "age":19
          },
          "phone":"92779392",
          "cell":"12178009",
          "id":{
             "name":"CPR",
             "value":"140387-8671"
          },
          "picture":{
             "large":"https://randomuser.me/api/portraits/women/61.jpg",
             "medium":"https://randomuser.me/api/portraits/med/women/61.jpg",
             "thumbnail":"https://randomuser.me/api/portraits/thumb/women/61.jpg"
          },
          "nat":"DK"
       },
       {
          "gender":"male",
          "name":{
             "title":"Mr",
             "first":"Benjamin",
             "last":"Zhang"
          },
          "location":{
             "street":{
                "number":7271,
                "name":"Northcote Road"
             },
             "city":"Christchurch",
             "state":"Nelson",
             "country":"New Zealand",
             "postcode":62427,
             "coordinates":{
                "latitude":"-42.2674",
                "longitude":"9.7327"
             },
             "timezone":{
                "offset":"+4:00",
                "description":"Abu Dhabi, Muscat, Baku, Tbilisi"
             }
          },
          "email":"benjamin.zhang@example.com",
          "login":{
             "uuid":"998101f0-7277-45e1-8c28-5b83f4f3562f",
             "username":"heavyleopard970",
             "password":"wings",
             "salt":"RgUiWpZf",
             "md5":"154f27d9c8d1cf4bb4ec38f4d0d4992c",
             "sha1":"45057930f5d4bd99aee963ecd0c3ab5da0c02104",
             "sha256":"bc36e3624836e12a6155a03c98aeb1ba040cbe0e1033e2c36bbf9cf88036ee80"
          },
          "dob":{
             "date":"1983-06-29T22:00:59.691Z",
             "age":39
          },
          "registered":{
             "date":"2008-12-28T19:31:03.165Z",
             "age":13
          },
          "phone":"(768)-213-1081",
          "cell":"(895)-834-0530",
          "id":{
             "name":"",
             "value":null
          },
          "picture":{
             "large":"https://randomuser.me/api/portraits/men/10.jpg",
             "medium":"https://randomuser.me/api/portraits/med/men/10.jpg",
             "thumbnail":"https://randomuser.me/api/portraits/thumb/men/10.jpg"
          },
          "nat":"NZ"
       },
       {
          "gender":"male",
          "name":{
             "title":"Mr",
             "first":"Geart",
             "last":"Van der Stelt"
          },
          "location":{
             "street":{
                "number":710,
                "name":"J W Dumonstraat"
             },
             "city":"Buinen",
             "state":"Utrecht",
             "country":"Netherlands",
             "postcode":"6310 JP",
             "coordinates":{
                "latitude":"64.0128",
                "longitude":"-33.9488"
             },
             "timezone":{
                "offset":"+9:00",
                "description":"Tokyo, Seoul, Osaka, Sapporo, Yakutsk"
             }
          },
          "email":"geart.vanderstelt@example.com",
          "login":{
             "uuid":"442df7e4-0063-434b-8099-d37e10b36339",
             "username":"sadkoala872",
             "password":"kimberly",
             "salt":"0YSv1Hii",
             "md5":"98d41b84a4e375a4cf50b94da8df0b2c",
             "sha1":"2385eec7acbe4d7d175b9d9b9337f754e3a38ea9",
             "sha256":"a3d32663fbde5b80b2e6315882a109ce6151b2573afe270d407250f3cb3de80f"
          },
          "dob":{
             "date":"1968-01-13T14:12:54.106Z",
             "age":54
          },
          "registered":{
             "date":"2008-09-18T05:15:48.800Z",
             "age":14
          },
          "phone":"(010) 4240922",
          "cell":"(06) 57729379",
          "id":{
             "name":"BSN",
             "value":"03277272"
          },
          "picture":{
             "large":"https://randomuser.me/api/portraits/men/22.jpg",
             "medium":"https://randomuser.me/api/portraits/med/men/22.jpg",
             "thumbnail":"https://randomuser.me/api/portraits/thumb/men/22.jpg"
          },
          "nat":"NL"
       },
       {
          "gender":"male",
          "name":{
             "title":"Mr",
             "first":"Babür",
             "last":"Keçeci"
          },
          "location":{
             "street":{
                "number":4124,
                "name":"Filistin Cd"
             },
             "city":"Sinop",
             "state":"Van",
             "country":"Turkey",
             "postcode":57187,
             "coordinates":{
                "latitude":"-44.4831",
                "longitude":"-72.0838"
             },
             "timezone":{
                "offset":"+3:00",
                "description":"Baghdad, Riyadh, Moscow, St. Petersburg"
             }
          },
          "email":"babur.kececi@example.com",
          "login":{
             "uuid":"666a7329-48fb-4972-af31-da0984b12b05",
             "username":"yellowleopard833",
             "password":"jetta",
             "salt":"RhOIIygP",
             "md5":"449216912d507c7852bcd41ee06a4cc4",
             "sha1":"acb2cae811b4a1c5a15bc59685e3fc35911e333a",
             "sha256":"2389273a17dc3636a365e0e1af7e1009a3f153e7a87025964cb1e06cdb0834fe"
          },
          "dob":{
             "date":"1982-02-02T01:57:35.405Z",
             "age":40
          },
          "registered":{
             "date":"2005-09-14T03:16:33.455Z",
             "age":17
          },
          "phone":"(668)-169-1867",
          "cell":"(935)-864-5067",
          "id":{
             "name":"",
             "value":null
          },
          "picture":{
             "large":"https://randomuser.me/api/portraits/men/98.jpg",
             "medium":"https://randomuser.me/api/portraits/med/men/98.jpg",
             "thumbnail":"https://randomuser.me/api/portraits/thumb/men/98.jpg"
          },
          "nat":"TR"
       },
       {
          "gender":"male",
          "name":{
             "title":"Mr",
             "first":"Alvaro",
             "last":"Verduzco"
          },
          "location":{
             "street":{
                "number":8910,
                "name":"Periférico Tamaulipas"
             },
             "city":"Arriaga",
             "state":"Puebla",
             "country":"Mexico",
             "postcode":17906,
             "coordinates":{
                "latitude":"-22.4441",
                "longitude":"-138.6509"
             },
             "timezone":{
                "offset":"+6:00",
                "description":"Almaty, Dhaka, Colombo"
             }
          },
          "email":"alvaro.verduzco@example.com",
          "login":{
             "uuid":"b2211156-28e6-42ac-a30a-c699034bc95e",
             "username":"purpletiger854",
             "password":"manuel",
             "salt":"7H84ZAP6",
             "md5":"543daccaf7c8801570a1efb3cfab7c13",
             "sha1":"2f66153f586ba58b7ed0ac5b0b2c7a41f1d7ab03",
             "sha256":"765bb17159cbfdac59db3fee20e8522b314b15fb5352647cd4903aaeff31088e"
          },
          "dob":{
             "date":"1984-10-11T14:05:33.752Z",
             "age":38
          },
          "registered":{
             "date":"2002-10-01T13:06:20.157Z",
             "age":20
          },
          "phone":"(694) 484 2812",
          "cell":"(611) 783 8116",
          "id":{
             "name":"NSS",
             "value":"04 24 04 4713 6"
          },
          "picture":{
             "large":"https://randomuser.me/api/portraits/men/66.jpg",
             "medium":"https://randomuser.me/api/portraits/med/men/66.jpg",
             "thumbnail":"https://randomuser.me/api/portraits/thumb/men/66.jpg"
          },
          "nat":"MX"
       },
       {
          "gender":"male",
          "name":{
             "title":"Mr",
             "first":"Luukas",
             "last":"Kurtti"
          },
          "location":{
             "street":{
                "number":9076,
                "name":"Rotuaari"
             },
             "city":"Punkaharju",
             "state":"Ostrobothnia",
             "country":"Finland",
             "postcode":36364,
             "coordinates":{
                "latitude":"44.0629",
                "longitude":"70.1190"
             },
             "timezone":{
                "offset":"+5:45",
                "description":"Kathmandu"
             }
          },
          "email":"luukas.kurtti@example.com",
          "login":{
             "uuid":"a0dff06a-11fe-45fe-926f-af64312ffd4f",
             "username":"beautifulcat146",
             "password":"closeup",
             "salt":"HwSZYqKm",
             "md5":"491380bd5044088944360edcc23e640d",
             "sha1":"4a3754d513882e2d800672efbe36140d0fe10a91",
             "sha256":"70b19a167e4924e2dae6ed5bb7cff166beba466ef3d0670be67b96125521fcc6"
          },
          "dob":{
             "date":"1979-05-28T14:24:19.908Z",
             "age":43
          },
          "registered":{
             "date":"2017-11-03T19:27:51.774Z",
             "age":5
          },
          "phone":"08-816-437",
          "cell":"045-655-70-64",
          "id":{
             "name":"HETU",
             "value":"NaNNA327undefined"
          },
          "picture":{
             "large":"https://randomuser.me/api/portraits/men/1.jpg",
             "medium":"https://randomuser.me/api/portraits/med/men/1.jpg",
             "thumbnail":"https://randomuser.me/api/portraits/thumb/men/1.jpg"
          },
          "nat":"FI"
       },
       {
          "gender":"male",
          "name":{
             "title":"Mr",
             "first":"Blake",
             "last":"Anderson"
          },
          "location":{
             "street":{
                "number":6905,
                "name":"Argyle St"
             },
             "city":"Odessa",
             "state":"Newfoundland and Labrador",
             "country":"Canada",
             "postcode":"F7E 3D4",
             "coordinates":{
                "latitude":"-72.2585",
                "longitude":"159.4706"
             },
             "timezone":{
                "offset":"-2:00",
                "description":"Mid-Atlantic"
             }
          },
          "email":"blake.anderson@example.com",
          "login":{
             "uuid":"05f1bb87-e2c1-454c-9d80-f24cbe53c1c4",
             "username":"smallmouse237",
             "password":"butter",
             "salt":"OY4xFlUy",
             "md5":"81e86461514739796ddcaa4613ac65fd",
             "sha1":"c43aacf3d410ff8e85cb07032ab8fdc34880be81",
             "sha256":"2b9a630bdf357e60a7a001d2a485ef06e7ff290155e07a2a03657e4fec595ace"
          },
          "dob":{
             "date":"1991-12-26T10:20:39.984Z",
             "age":30
          },
          "registered":{
             "date":"2008-05-10T21:34:12.833Z",
             "age":14
          },
          "phone":"W59 U69-3603",
          "cell":"J23 P83-4634",
          "id":{
             "name":"SIN",
             "value":"735608788"
          },
          "picture":{
             "large":"https://randomuser.me/api/portraits/men/28.jpg",
             "medium":"https://randomuser.me/api/portraits/med/men/28.jpg",
             "thumbnail":"https://randomuser.me/api/portraits/thumb/men/28.jpg"
          },
          "nat":"CA"
       },
       {
          "gender":"female",
          "name":{
             "title":"Miss",
             "first":"Sapthashree",
             "last":"Bhoja"
          },
          "location":{
             "street":{
                "number":7320,
                "name":"Tripolia Bazar"
             },
             "city":"Hazaribagh",
             "state":"Jammu and Kashmir",
             "country":"India",
             "postcode":62516,
             "coordinates":{
                "latitude":"-54.1947",
                "longitude":"-170.8011"
             },
             "timezone":{
                "offset":"-8:00",
                "description":"Pacific Time (US & Canada)"
             }
          },
          "email":"sapthashree.bhoja@example.com",
          "login":{
             "uuid":"4e9b1ae4-ccf5-4f32-82bd-11feab1c62fa",
             "username":"tinybutterfly374",
             "password":"capricor",
             "salt":"I56aJClz",
             "md5":"1586fa3742380e43e8b8e0f11e8cab69",
             "sha1":"47f5b68b0632d541f37c78c0a139fa4d8cf9e696",
             "sha256":"3cf803d1923b299f4b29c5ca04fdda8e3e91d9d504dd3421a490b986d264194d"
          },
          "dob":{
             "date":"1987-08-29T08:05:29.655Z",
             "age":35
          },
          "registered":{
             "date":"2010-11-24T01:05:22.219Z",
             "age":12
          },
          "phone":"8548683205",
          "cell":"8980412220",
          "id":{
             "name":"UIDAI",
             "value":"549700292688"
          },
          "picture":{
             "large":"https://randomuser.me/api/portraits/women/29.jpg",
             "medium":"https://randomuser.me/api/portraits/med/women/29.jpg",
             "thumbnail":"https://randomuser.me/api/portraits/thumb/women/29.jpg"
          },
          "nat":"IN"
       },
       {
          "gender":"male",
          "name":{
             "title":"Mr",
             "first":"Joel",
             "last":"Perko"
          },
          "location":{
             "street":{
                "number":6252,
                "name":"Reijolankatu"
             },
             "city":"Oulu",
             "state":"Pirkanmaa",
             "country":"Finland",
             "postcode":64991,
             "coordinates":{
                "latitude":"40.8827",
                "longitude":"36.0133"
             },
             "timezone":{
                "offset":"-6:00",
                "description":"Central Time (US & Canada), Mexico City"
             }
          },
          "email":"joel.perko@example.com",
          "login":{
             "uuid":"179b1b2c-4d1f-478f-a51c-bd42530e2cf8",
             "username":"redbear467",
             "password":"albatros",
             "salt":"oUz0OGAU",
             "md5":"b3f1adc1c34a32a817dcc758a0326f68",
             "sha1":"669150afaa53d989cf5cd00e61a527b6b2a5c6ce",
             "sha256":"0af71b7d36040bf36b15fb9670b98c120f4d3d9e59e77a3bb74634b76370a2b3"
          },
          "dob":{
             "date":"1944-11-05T16:14:34.301Z",
             "age":78
          },
          "registered":{
             "date":"2003-04-02T09:20:04.304Z",
             "age":19
          },
          "phone":"08-295-564",
          "cell":"046-174-70-27",
          "id":{
             "name":"HETU",
             "value":"NaNNA371undefined"
          },
          "picture":{
             "large":"https://randomuser.me/api/portraits/men/53.jpg",
             "medium":"https://randomuser.me/api/portraits/med/men/53.jpg",
             "thumbnail":"https://randomuser.me/api/portraits/thumb/men/53.jpg"
          },
          "nat":"FI"
       },
       {
          "gender":"male",
          "name":{
             "title":"Mr",
             "first":"Rasmus",
             "last":"Tikkanen"
          },
          "location":{
             "street":{
                "number":9079,
                "name":"Satakennankatu"
             },
             "city":"Hyrynsalmi",
             "state":"North Karelia",
             "country":"Finland",
             "postcode":16023,
             "coordinates":{
                "latitude":"68.9298",
                "longitude":"-48.2293"
             },
             "timezone":{
                "offset":"+4:00",
                "description":"Abu Dhabi, Muscat, Baku, Tbilisi"
             }
          },
          "email":"rasmus.tikkanen@example.com",
          "login":{
             "uuid":"70950a24-ce1c-42c4-bcb5-d8228b7d6532",
             "username":"goldenpeacock944",
             "password":"stacie",
             "salt":"kbF8q2TY",
             "md5":"59389034618bb84a09b772e581adb23c",
             "sha1":"d1f96dea9530c35449e8cbc4dd5b619f83658149",
             "sha256":"30b207159eb8a18c1ec3d916536ef39006d323811846f09d843cbfe1a3243cba"
          },
          "dob":{
             "date":"1975-05-03T22:37:04.502Z",
             "age":47
          },
          "registered":{
             "date":"2010-12-12T02:22:50.276Z",
             "age":11
          },
          "phone":"08-156-597",
          "cell":"040-336-18-85",
          "id":{
             "name":"HETU",
             "value":"NaNNA765undefined"
          },
          "picture":{
             "large":"https://randomuser.me/api/portraits/men/12.jpg",
             "medium":"https://randomuser.me/api/portraits/med/men/12.jpg",
             "thumbnail":"https://randomuser.me/api/portraits/thumb/men/12.jpg"
          },
          "nat":"FI"
       },
       {
          "gender":"female",
          "name":{
             "title":"Miss",
             "first":"Lucy",
             "last":"Petit"
          },
          "location":{
             "street":{
                "number":1943,
                "name":"Rue du Moulin"
             },
             "city":"Perpignan",
             "state":"Essonne",
             "country":"France",
             "postcode":52965,
             "coordinates":{
                "latitude":"-84.6712",
                "longitude":"-6.0031"
             },
             "timezone":{
                "offset":"-3:30",
                "description":"Newfoundland"
             }
          },
          "email":"lucy.petit@example.com",
          "login":{
             "uuid":"370e43e2-6606-406b-b9bc-3e5cf054cc3c",
             "username":"lazygoose220",
             "password":"searay",
             "salt":"z81twt1l",
             "md5":"caf8fc36a098d8763bda29378c69c900",
             "sha1":"2ed7e9aa8bbfabfbe92d1cd0d99edf070122b4aa",
             "sha256":"869db0eae9e1df6298d07aa17fb12c50077c5e29accfdae4ccd386a6342e44a9"
          },
          "dob":{
             "date":"1985-06-19T21:36:04.871Z",
             "age":37
          },
          "registered":{
             "date":"2014-09-25T19:28:05.690Z",
             "age":8
          },
          "phone":"05-32-20-29-22",
          "cell":"06-92-71-62-59",
          "id":{
             "name":"INSEE",
             "value":"2850556618155 52"
          },
          "picture":{
             "large":"https://randomuser.me/api/portraits/women/75.jpg",
             "medium":"https://randomuser.me/api/portraits/med/women/75.jpg",
             "thumbnail":"https://randomuser.me/api/portraits/thumb/women/75.jpg"
          },
          "nat":"FR"
       },
       {
          "gender":"male",
          "name":{
             "title":"Mr",
             "first":"Andreas",
             "last":"Schindler"
          },
          "location":{
             "street":{
                "number":507,
                "name":"Birkenweg"
             },
             "city":"Spalt",
             "state":"Baden-Württemberg",
             "country":"Germany",
             "postcode":74746,
             "coordinates":{
                "latitude":"-36.1068",
                "longitude":"38.7792"
             },
             "timezone":{
                "offset":"+10:00",
                "description":"Eastern Australia, Guam, Vladivostok"
             }
          },
          "email":"andreas.schindler@example.com",
          "login":{
             "uuid":"62159e01-8969-4bc8-b2a8-861a7f8da2fb",
             "username":"lazyfish324",
             "password":"cattle",
             "salt":"V6TEjzwd",
             "md5":"57cbe3fa9b550501ce0463ee74ba4f25",
             "sha1":"43771c7a3a0cf450328ca5cae27f7189fdb33ffa",
             "sha256":"da271125855559fd6c790c426dbd89267aea94b059f77a7277581f2b99a73174"
          },
          "dob":{
             "date":"1957-09-14T10:27:01.074Z",
             "age":65
          },
          "registered":{
             "date":"2011-08-11T08:05:10.501Z",
             "age":11
          },
          "phone":"0931-1625825",
          "cell":"0179-6660399",
          "id":{
             "name":"SVNR",
             "value":"58 140957 S 071"
          },
          "picture":{
             "large":"https://randomuser.me/api/portraits/men/20.jpg",
             "medium":"https://randomuser.me/api/portraits/med/men/20.jpg",
             "thumbnail":"https://randomuser.me/api/portraits/thumb/men/20.jpg"
          },
          "nat":"DE"
       },
       {
          "gender":"male",
          "name":{
             "title":"Monsieur",
             "first":"Timothy",
             "last":"Morel"
          },
          "location":{
             "street":{
                "number":8926,
                "name":"Avenue du Fort-Caire"
             },
             "city":"Vandoeuvres",
             "state":"Uri",
             "country":"Switzerland",
             "postcode":8927,
             "coordinates":{
                "latitude":"22.7121",
                "longitude":"120.1941"
             },
             "timezone":{
                "offset":"-6:00",
                "description":"Central Time (US & Canada), Mexico City"
             }
          },
          "email":"timothy.morel@example.com",
          "login":{
             "uuid":"2ae2dacf-59d9-4781-9ba0-1fced0a1f8fe",
             "username":"orangerabbit909",
             "password":"ministry",
             "salt":"ic5Pf3DA",
             "md5":"cbd4b629cbd6aeaf6ae1365c61c7f531",
             "sha1":"8b959ee1a14995db4d625d4a77843c4dee50b9b1",
             "sha256":"c62b474b5191d7b0ee4fff8d19bc6a0c49c902c537a7b0aecb8dd3d72cd0581a"
          },
          "dob":{
             "date":"1964-12-23T02:40:36.683Z",
             "age":57
          },
          "registered":{
             "date":"2020-01-12T04:01:12.804Z",
             "age":2
          },
          "phone":"076 402 12 39",
          "cell":"077 423 84 48",
          "id":{
             "name":"AVS",
             "value":"756.4847.6959.58"
          },
          "picture":{
             "large":"https://randomuser.me/api/portraits/men/63.jpg",
             "medium":"https://randomuser.me/api/portraits/med/men/63.jpg",
             "thumbnail":"https://randomuser.me/api/portraits/thumb/men/63.jpg"
          },
          "nat":"CH"
       },
       {
          "gender":"male",
          "name":{
             "title":"Mr",
             "first":"Okan",
             "last":"Türkyılmaz"
          },
          "location":{
             "street":{
                "number":6575,
                "name":"Fatih Sultan Mehmet Cd"
             },
             "city":"Diyarbakır",
             "state":"Ardahan",
             "country":"Turkey",
             "postcode":49513,
             "coordinates":{
                "latitude":"59.2399",
                "longitude":"-25.3563"
             },
             "timezone":{
                "offset":"-5:00",
                "description":"Eastern Time (US & Canada), Bogota, Lima"
             }
          },
          "email":"okan.turkyilmaz@example.com",
          "login":{
             "uuid":"ae9aedb0-af67-4e63-a341-1cc5e22a1737",
             "username":"heavybird744",
             "password":"bugs",
             "salt":"jRK370xN",
             "md5":"507f41262f94eb30cce5b452f5399a23",
             "sha1":"04db189cc378f0afaa54bb14240979d3fb7abfaa",
             "sha256":"8aca44a212b6d97ae58b50cde5cde8cf2fcb42d64385c447da297e8abef27c36"
          },
          "dob":{
             "date":"1984-02-23T10:07:37.608Z",
             "age":38
          },
          "registered":{
             "date":"2012-01-10T17:29:18.018Z",
             "age":10
          },
          "phone":"(863)-450-0318",
          "cell":"(020)-484-8688",
          "id":{
             "name":"",
             "value":null
          },
          "picture":{
             "large":"https://randomuser.me/api/portraits/men/48.jpg",
             "medium":"https://randomuser.me/api/portraits/med/men/48.jpg",
             "thumbnail":"https://randomuser.me/api/portraits/thumb/men/48.jpg"
          },
          "nat":"TR"
       },
       {
          "gender":"male",
          "name":{
             "title":"Mr",
             "first":"Alexandre",
             "last":"Jean-Baptiste"
          },
          "location":{
             "street":{
                "number":2207,
                "name":"Coastal Highway"
             },
             "city":"Jasper",
             "state":"Alberta",
             "country":"Canada",
             "postcode":"X7J 9S0",
             "coordinates":{
                "latitude":"-79.0886",
                "longitude":"-6.5010"
             },
             "timezone":{
                "offset":"+4:00",
                "description":"Abu Dhabi, Muscat, Baku, Tbilisi"
             }
          },
          "email":"alexandre.jean-baptiste@example.com",
          "login":{
             "uuid":"7c36a518-6beb-4a84-85bd-d49330109c0c",
             "username":"smallleopard491",
             "password":"scotland",
             "salt":"ZOcE6keA",
             "md5":"fabe012c0f3d353d6923781fce3f4b75",
             "sha1":"cebc288fa6b86678dd640cc2458571aa1ceb0f13",
             "sha256":"eb66424fe2a2dc9ca5699608c6170ea1eb0c8c7930fe6ed3bbc649ac2d816ba5"
          },
          "dob":{
             "date":"1997-12-23T23:29:45.213Z",
             "age":24
          },
          "registered":{
             "date":"2016-01-23T04:47:22.575Z",
             "age":6
          },
          "phone":"C87 N35-5840",
          "cell":"S74 M33-3436",
          "id":{
             "name":"SIN",
             "value":"477460307"
          },
          "picture":{
             "large":"https://randomuser.me/api/portraits/men/60.jpg",
             "medium":"https://randomuser.me/api/portraits/med/men/60.jpg",
             "thumbnail":"https://randomuser.me/api/portraits/thumb/men/60.jpg"
          },
          "nat":"CA"
       }
    ],
    "info":{
       "seed":"66544aa177b59352",
       "results":20,
       "page":1,
       "version":"1.4"
    }
 }